etc/udev/rules.d/10-stoq.rules
stoq/__init__.py
stoq/__installed__.py
stoq/dbadmin.py
stoq/main.py
stoq/gui/__init__.py
stoq/gui/accounts.py
stoq/gui/admin.py
stoq/gui/calendar.py
stoq/gui/config.py
stoq/gui/delivery.py
stoq/gui/financial.py
stoq/gui/inventory.py
stoq/gui/launcher.py
stoq/gui/payable.py
stoq/gui/pos.py
stoq/gui/production.py
stoq/gui/purchase.py
stoq/gui/receivable.py
stoq/gui/sales.py
stoq/gui/services.py
stoq/gui/stock.py
stoq/gui/till.py
stoq/gui/update.py
stoq/gui/welcomedialog.py
stoq/gui/widgets.py
stoq/gui/shell/__init__.py
stoq/gui/shell/bootstrap.py
stoq/gui/shell/shell.py
stoq/gui/shell/shellapp.py
stoq/gui/shell/shellwindow.py
stoq/gui/shell/statusbar.py
stoq/gui/test/__init__.py
stoq/gui/test/baseguitest.py
stoq/gui/test/test_admin.py
stoq/gui/test/test_calendar.py
stoq/gui/test/test_config_wizard.py
stoq/gui/test/test_delivery.py
stoq/gui/test/test_financial.py
stoq/gui/test/test_inventory.py
stoq/gui/test/test_launcher.py
stoq/gui/test/test_main.py
stoq/gui/test/test_payable.py
stoq/gui/test/test_pos.py
stoq/gui/test/test_production.py
stoq/gui/test/test_purchase.py
stoq/gui/test/test_receivable.py
stoq/gui/test/test_sales.py
stoq/gui/test/test_services.py
stoq/gui/test/test_statusbar.py
stoq/gui/test/test_stock.py
stoq/gui/test/test_till.py
stoq/lib/__init__.py
stoq/lib/applist.py
stoq/lib/dependencies.py
stoq/lib/options.py
stoq/lib/startup.py
stoq-4.7.0.data/data/share/applications/stoq.desktop
stoq-4.7.0.data/data/share/doc/stoq/AUTHORS
stoq-4.7.0.data/data/share/doc/stoq/CONTRIBUTORS
stoq-4.7.0.data/data/share/doc/stoq/COPYING
stoq-4.7.0.data/data/share/doc/stoq/COPYING.pt_BR
stoq-4.7.0.data/data/share/doc/stoq/COPYING.stoqlib
stoq-4.7.0.data/data/share/doc/stoq/README
stoq-4.7.0.data/data/share/doc/stoq/copyright
stoq-4.7.0.data/data/share/gnome/help/stoq/C/about.page
stoq-4.7.0.data/data/share/gnome/help/stoq/C/account-payable-new.page
stoq-4.7.0.data/data/share/gnome/help/stoq/C/account-payable-pay.page
stoq-4.7.0.dist-info/AUTHORS
stoq-4.7.0.dist-info/COPYING
stoq-4.7.0.dist-info/COPYING.pt_BR
stoq-4.7.0.dist-info/COPYING.stoqlib
stoq-4.7.0.dist-info/METADATA
stoq-4.7.0.dist-info/WHEEL
stoq-4.7.0.dist-info/top_level.txt
stoq-4.7.0.dist-info/RECORD
