Metadata-Version: 2.1
Name: stoq
Version: 4.7.0
Summary: A powerful retail system
Home-page: http://www.stoq.com.br
Author: Async Open Source
Author-email: stoq-devel@async.com.br
License: GNU GPL 2.0 and GNU LGPL 2.1 (see COPYING and COPYING.stoqlib)
Platform: UNKNOWN
Requires-Dist: Mako (>=0.2.5)
Requires-Dist: Pillow (>=3.1.0)
Requires-Dist: PyGObject (>=3.30.1)
Requires-Dist: blinker (>=1.3)
Requires-Dist: cryptography (>=1.4)
Requires-Dist: future (>=0.15)
Requires-Dist: kiwi-gtk (>=3.0)
Requires-Dist: lxml (>=3.3.3)
Requires-Dist: psycopg2 (>=2.0.5)
Requires-Dist: pyinotify (>=0.9.2)
Requires-Dist: pyjwt (>=1.3.0)
Requires-Dist: pykcs11 (>=1.3.2)
Requires-Dist: pyopenssl (>=0.16.0)
Requires-Dist: python-dateutil (>=1.4.1)
Requires-Dist: python-nss (>=0.12)
Requires-Dist: qrcode (>=4.0)
Requires-Dist: raven (>=5.1.1)
Requires-Dist: reportlab (>=2.4)
Requires-Dist: requests (>=2.18.4)
Requires-Dist: stoqdrivers (>=1.6)
Requires-Dist: storm @ https://launchpad.net/~stoq-dev/+archive/ubuntu/lancamentos/+sourcefiles/storm/0.20.0.100-2~py3-1xenial/storm_0.20.0.100-2~py3-1xenial.tar.gz#egg=storm
Requires-Dist: viivakoodi (>=0.8.0)
Requires-Dist: weasyprint (>=0.15)
Requires-Dist: xlwt (>=0.7.2)
Requires-Dist: zope.interface (>=3.0)
